<?xml version="1.0" encoding="UTF-8" standalone="no" ?>
<event_message alg_vers="1.0.0 2018-02-23" category="test" instance="jrand-contour@trinitite" message_type="update" orig_sys="eqinfo2gm" ref_id="0" ref_src="" timestamp="2013-03-01T21:53:14.000Z" version="37">

  <core_info id="FinDer_Mendocino_M7.8">
    <mag units="Mw">7.8000</mag>
    <mag_uncer units="Mw">0.3536</mag_uncer>
    <lat units="deg">40.3500</lat>
    <lat_uncer units="deg">0.3536</lat_uncer>
    <lon units="deg">-124.9500</lon>
    <lon_uncer units="deg">0.3536</lon_uncer>
    <depth units="km">5.0000</depth>
    <depth_uncer units="km">50.0000</depth_uncer>
    <orig_time units="UTC">2013-03-01T21:51:56.000Z</orig_time>
    <orig_time_uncer units="sec">20.0000</orig_time_uncer>
    <likelihood>1.0000</likelihood>
    <num_stations>0</num_stations>
  </core_info>

  <contributors>
    <contributor alg_instance="-" alg_name="dm" alg_version="-" category="test" event_id="FinDer_Mendocino_M7.8" version="37"/>
  </contributors>

  <fault_info>
    <finite_fault atten_geom="true" segment_number="1" segment_shape="line">
      <segment>
        <vertices>
          <vertex>
            <lat units="deg">40.3567</lat>
            <lon units="deg">-124.9432</lon>
            <depth units="">0.0000</depth>
          </vertex>
          <vertex>
            <lat units="deg">40.3446</lat>
            <lon units="deg">-124.8892</lon>
            <depth units="">0.0000</depth>
          </vertex>
          <vertex>
            <lat units="deg">40.3319</lat>
            <lon units="deg">-124.8352</lon>
            <depth units="">0.0000</depth>
          </vertex>
          <vertex>
            <lat units="deg">40.2630</lat>
            <lon units="deg">-124.4572</lon>
            <depth units="">0.0000</depth>
          </vertex>
          <vertex>
            <lat units="deg">39.9358</lat>
            <lon units="deg">-124.0162</lon>
            <depth units="">0.0000</depth>
          </vertex>
          <vertex>
            <lat units="deg">39.7084</lat>
            <lon units="deg">-123.9982</lon>
            <depth units="">0.0000</depth>
          </vertex>
          <vertex>
            <lat units="deg">39.4729</lat>
            <lon units="deg">-123.9442</lon>
            <depth units="">0.0000</depth>
          </vertex>
          <vertex>
            <lat units="deg">39.1234</lat>
            <lon units="deg">-123.7732</lon>
            <depth units="">0.0000</depth>
          </vertex>
          <vertex>
            <lat units="deg">38.9082</lat>
            <lon units="deg">-123.6112</lon>
            <depth units="">0.0000</depth>
          </vertex>
          <vertex>
            <lat units="deg">38.8772</lat>
            <lon units="deg">-123.5842</lon>
            <depth units="">0.0000</depth>
          </vertex>
        </vertices>
      </segment>
    </finite_fault>
  </fault_info>

  <gm_info>
    <gmcontour_pred number="8">
      <contour>
        <MMI units="">2.0000</MMI>
        <PGA units="cm/s/s">2.8480</PGA>
        <PGV units="cm/s">0.2154</PGV>
        <polygon number="8">41.0113,-132.1504 45.7827,-123.6872 43.0516,-118.4957 42.3160,-117.8884 37.7966,-116.7034 33.4399,-124.6339 35.8935,-129.4313 36.6298,-130.1632 41.0113,-132.1504</polygon>
      </contour>
      <contour>
        <MMI units="">3.0000</MMI>
        <PGA units="cm/s/s">8.1113</PGA>
        <PGV units="cm/s">0.6449</PGV>
        <polygon number="8">40.8688,-130.0591 44.2201,-124.0726 42.2019,-120.3160 41.4642,-119.6857 38.1492,-118.6652 35.0081,-124.3459 36.8860,-127.8943 37.6240,-128.6130 40.8688,-130.0591</polygon>
      </contour>
      <contour>
        <MMI units="">4.0000</MMI>
        <PGA units="cm/s/s">23.1013</PGA>
        <PGV units="cm/s">1.9307</PGV>
        <polygon number="8">40.7023,-128.1217 42.7646,-124.4135 41.3857,-121.9662 40.6467,-121.3161 38.4477,-120.5076 36.4671,-124.0678 37.7916,-126.4277 38.5306,-127.1328 40.7023,-128.1217</polygon>
      </contour>
      <contour>
        <MMI units="">5.0000</MMI>
        <PGA units="cm/s/s">65.7933</PGA>
        <PGV units="cm/s">5.7797</PGV>
        <polygon number="8">40.5368,-126.4949 41.5356,-124.6888 40.6790,-123.3264 39.9395,-122.6608 38.6770,-122.0737 37.6978,-123.8248 38.5413,-125.1621 39.2809,-125.8546 40.5368,-126.4949</polygon>
      </contour>
      <contour>
        <MMI units="">6.0000</MMI>
        <PGA units="cm/s/s">123.8500</PGA>
        <PGV units="cm/s">11.2687</PGV>
        <polygon number="8">40.4525,-125.7452 40.9669,-124.8127 40.3468,-123.9458 39.6071,-123.2734 38.7760,-122.8014 38.2668,-123.7097 38.8834,-124.5678 39.6231,-125.2542 40.4525,-125.7452</polygon>
      </contour>
      <contour>
        <MMI units="">7.0000</MMI>
        <PGA units="cm/s/s">232.3380</PGA>
        <PGV units="cm/s">21.8805</PGV>
        <polygon number="8">40.3953,-125.2608 40.5985,-124.8918 40.1299,-124.3437 39.3902,-123.6669 38.8377,-123.2737 38.6353,-123.6342 39.1034,-124.1799 39.8431,-124.8622 40.3953,-125.2608</polygon>
      </contour>
      <contour>
        <MMI units="">8.0000</MMI>
        <PGA units="cm/s/s">435.8572</PGA>
        <PGV units="cm/s">42.4856</PGV>
        <polygon number="8">40.3669,-125.0260 40.4198,-124.9298 40.0242,-124.5358 39.2844,-123.8570 38.8670,-123.5032 38.8141,-123.5973 39.2097,-123.9908 39.9494,-124.6710 40.3669,-125.0260</polygon>
      </contour>
      <contour>
        <MMI units="">9.0000</MMI>
        <PGA units="cm/s/s">817.6516</PGA>
        <PGV units="cm/s">82.4948</PGV>
        <polygon number="8">40.3590,-124.9620 40.3710,-124.9402 39.9953,-124.5881 39.2556,-123.9088 38.8749,-123.5658 38.8629,-123.5872 39.2386,-123.9391 39.9783,-124.6188 40.3590,-124.9620</polygon>
      </contour>
    </gmcontour_pred>
  </gm_info>

</event_message>


